{
    "algo_type": "TRAVERSAL_SCHEME",
    "dataset": "/GPUFS/nsccgz_zgchen_2/zyl/ppopp19-artifact/dataset/soc-orkut/soc-orkut.undirected.random.weight.gr",
    "device": "Tesla V100-SXM2-16GB",
    "force_pull_load_balancing": "FINE_GRAINED",
    "force_push_load_balancing": "FINE_GRAINED",
    "fused_kernel": "NO",
    "max_iteration_reached": "NO",
    "nedges": 212698418,
    "nnodes": 2997166,
    "num_iteration": 20,
    "priority_type": "none",
    "time_bitmap2queue": 0.0670000016689301,
    "time_input_active_node": 0.217000052332878,
    "time_input_workload": 0.310000032186508,
    "time_kernel": 77.7759857177734,
    "time_output_active_node": 0.192000031471252,
    "time_output_workload": 0.442000031471252,
    "time_per_round": 4.03704977035522,
    "time_priority_sample": 0.0,
    "time_queue2bitmap": 0.700999975204468,
    "time_rebuild_worklist": 0.0,
    "time_sort_worklist": 0.0,
    "time_total": 80.7409973144531,
    "time_unique_worklist": 0.0
}
